nrc_scrape/__init__.py
nrc_scrape/bulk_downloader.py
nrc_scrape/logs_setup.py
nrc_scrape/main.py
nrc_scrape/url_maker.py
nrc_scrape-0.0.5.dist-info/METADATA
nrc_scrape-0.0.5.dist-info/WHEEL
nrc_scrape-0.0.5.dist-info/top_level.txt
nrc_scrape-0.0.5.dist-info/RECORD
