Metadata-Version: 2.1
Name: nrc-scrape
Version: 0.0.5
Summary: Python package to scrape NRC Event Reports.
Home-page: https://github.com/bradfox2/nrc-scrape
Author: Bradley Fox
Author-email: bradfox2@gmail.com
License: UNKNOWN
Platform: UNKNOWN
Classifier: Programming Language :: Python :: 3
Classifier: License :: OSI Approved :: MIT License
Classifier: Operating System :: OS Independent
Requires-Python: >=3.7
Requires-Dist: beautifulsoup4 (==4.8.2)
Requires-Dist: numpy (==1.18.1)
Requires-Dist: pandas (==1.0.1)
Requires-Dist: python-dateutil (==2.8.1)
Requires-Dist: requests (==2.23.0)
